sisaptoolsDev/__init__.py
sisaptoolsDev/aes.py
sisaptoolsDev/constants.py
sisaptoolsDev/database.py
sisaptoolsDev/mail.py
sisaptoolsDev/redis.py
sisaptoolsDev/services.json
sisaptoolsDev/services.py
sisaptoolsDev/ssh.py
sisaptoolsDev/textfile.py
sisaptoolsDev-0.0.19.dist-info/METADATA
sisaptoolsDev-0.0.19.dist-info/WHEEL
sisaptoolsDev-0.0.19.dist-info/top_level.txt
sisaptoolsDev-0.0.19.dist-info/RECORD
