Metadata-Version: 2.1
Name: sisaptoolsDev
Version: 0.0.19
Summary: Eines per debugejar sisaptools (random-Stubs)
Home-page: UNKNOWN
Author: SIDIAP
Author-email: UNKNOWN
License: MIT
Keywords: database development debugin Stubs
Platform: UNKNOWN
Classifier: Development Status :: 2 - Pre-Alpha
Classifier: Intended Audience :: Developers
Classifier: Topic :: Software Development :: Debuggers
Classifier: License :: OSI Approved :: MIT License
Classifier: Programming Language :: Python :: 3
Requires-Dist: python-dateutil
